muiscaenergy-comun/__init__.py
muiscaenergy-comun/src/__init__.py
muiscaenergy-comun/src/eng_economy/__init__.py
muiscaenergy-comun/src/eng_economy/cashflow.py
muiscaenergy-comun/src/messages/__init__.py
muiscaenergy-comun/src/messages/base.py
muiscaenergy-comun/src/timeseries/__init__.py
muiscaenergy-comun/src/timeseries/base.py
muiscaenergy-comun/src/utils/__init__.py
muiscaenergy-comun/src/utils/mix.py
muiscaenergy-comun/test/__init__.py
muiscaenergy-comun/test/run_test.py
muiscaenergy-comun/test/eng_economy/__init__.py
muiscaenergy-comun/test/eng_economy/test_cashflow.py
muiscaenergy-comun/test/messages/__init__.py
muiscaenergy-comun/test/messages/test_base.py
muiscaenergy-comun/test/timeseries/__init__.py
muiscaenergy-comun/test/timeseries/test_base.py
muiscaenergy-comun/test/utils/__init__.py
muiscaenergy-comun/test/utils/test_mix.py
src/__init__.py
src/eng_economy/__init__.py
src/eng_economy/cashflow.py
src/messages/__init__.py
src/messages/base.py
src/timeseries/__init__.py
src/timeseries/base.py
src/utils/__init__.py
src/utils/mix.py
test/__init__.py
test/run_test.py
test/eng_economy/__init__.py
test/eng_economy/test_cashflow.py
test/messages/__init__.py
test/messages/test_base.py
test/timeseries/__init__.py
test/timeseries/test_base.py
test/utils/__init__.py
test/utils/test_mix.py
muiscaenergy_comun-0.0.3.dist-info/LICENSE
muiscaenergy_comun-0.0.3.dist-info/METADATA
muiscaenergy_comun-0.0.3.dist-info/WHEEL
muiscaenergy_comun-0.0.3.dist-info/top_level.txt
muiscaenergy_comun-0.0.3.dist-info/RECORD
