Metadata-Version: 2.1
Name: muiscaenergy-comun
Version: 0.0.3
Summary: common functions for muiscaenergy projects
Home-page: https://pypi.org/project/
Author: Jairo Hernando Cervantes Garcia
License: MIT license
Classifier: Development Status :: 1 - Planning
Classifier: Intended Audience :: Developers
Classifier: Intended Audience :: Science/Research
Classifier: License :: OSI Approved :: MIT License
Classifier: Natural Language :: English
Classifier: Programming Language :: Python :: 3.8
Requires-Python: >=3.10
License-File: LICENSE
Requires-Dist: timezonefinder (>=6.2.0)
Requires-Dist: pandas (>=1.5.3)
Provides-Extra: dev
Requires-Dist: pytest (>=7.0) ; extra == 'dev'
Requires-Dist: twine (>=4.0.2) ; extra == 'dev'
